gmns_ready/__init__.py
gmns_ready/build_network.py
gmns_ready/clean_network.py
gmns_ready/enhance_connectors.py
gmns_ready/extract_zones.py
gmns_ready/extract_zones_pop.py
gmns_ready/validate_accessibility.py
gmns_ready/validate_assignment.py
gmns_ready/validate_basemap.py
gmns_ready/validate_network.py
gmns_ready/GMNS_Tools/__init__.py
gmns_ready/GMNS_Tools/settings.csv
gmns_ready-0.0.9.dist-info/licenses/LICENSE.txt
gmns_ready-0.0.9.dist-info/METADATA
gmns_ready-0.0.9.dist-info/WHEEL
gmns_ready-0.0.9.dist-info/top_level.txt
gmns_ready-0.0.9.dist-info/RECORD
