Metadata-Version: 2.4
Name: gmns-ready
Version: 0.0.9
Summary: Tools for preparing and validating GMNS transportation network data
Author-email: Henan Zhu <henanzhu@asu.edu>, "Dr. Xuesong Zhou" <xzhou74@asu.edu>, "Dr. Han Zheng" <scholarhanzheng@gmail.com>
License: MIT
Project-URL: Homepage, https://github.com/hhhhhenanZ/gmns_ready
Project-URL: Bug Reports, https://github.com/hhhhhenanZ/gmns_ready/issues
Project-URL: Source, https://github.com/hhhhhenanZ/gmns_ready
Keywords: transportation,gmns,network-modeling,open-source,urban-planning,traffic-assignment
Classifier: Development Status :: 3 - Alpha
Classifier: Intended Audience :: Science/Research
Classifier: Topic :: Scientific/Engineering :: GIS
Classifier: Programming Language :: Python :: 3
Classifier: Programming Language :: Python :: 3.7
Classifier: Programming Language :: Python :: 3.8
Classifier: Programming Language :: Python :: 3.9
Classifier: Programming Language :: Python :: 3.10
Classifier: Programming Language :: Python :: 3.11
Classifier: Programming Language :: Python :: 3.12
Classifier: Operating System :: OS Independent
Requires-Python: >=3.7
License-File: LICENSE.txt
Requires-Dist: pandas>=1.3.0
Requires-Dist: numpy>=1.20.0
Requires-Dist: geopandas>=0.10.0
Requires-Dist: shapely>=1.8.0
Requires-Dist: geopy>=2.2.0
Requires-Dist: matplotlib>=3.3.0
Requires-Dist: networkx>=2.6.0
Requires-Dist: requests>=2.26.0
Requires-Dist: DTALite>=0.8.1
Dynamic: license-file
